sutdobfs/__init__.py
sutdobfs/__main__.py
sutdobfs/gatekeepers/__init__.py
sutdobfs/memes/jojo.txt
sutdobfs/memes/memes.txt
sutdobfs/providers/__init__.py
sutdobfs/providers/utils.py
sutdobfs-1.0.4.dist-info/LICENSE.md
sutdobfs-1.0.4.dist-info/METADATA
sutdobfs-1.0.4.dist-info/WHEEL
sutdobfs-1.0.4.dist-info/entry_points.txt
sutdobfs-1.0.4.dist-info/top_level.txt
sutdobfs-1.0.4.dist-info/RECORD
