Metadata-Version: 2.1
Name: sutdobfs
Version: 1.0.4
Summary: SUTD Obfuscator – Establish your variable names in collaboration with MIT
Home-page: https://github.com/OpenSUTD/sutdobfs
Author: Chester Koh
Author-email: chester8991@gmail.com
License: MIT
Platform: UNKNOWN
Classifier: License :: OSI Approved :: MIT License
Classifier: Programming Language :: Python :: 3
